dosemetrics/__init__.py
dosemetrics/_version.py
dosemetrics/dose.py
dosemetrics/structure_set.py
dosemetrics/structures.py
dosemetrics/io/__init__.py
dosemetrics/io/data_io.py
dosemetrics/io/dicom_io.py
dosemetrics/io/nifti_io.py
dosemetrics/metrics/__init__.py
dosemetrics/metrics/advanced_dvh.py
dosemetrics/metrics/conformity.py
dosemetrics/metrics/dose_comparison.py
dosemetrics/metrics/dvh.py
dosemetrics/metrics/gamma.py
dosemetrics/metrics/geometric.py
dosemetrics/metrics/homogeneity.py
dosemetrics/utils/__init__.py
dosemetrics/utils/analysis.py
dosemetrics/utils/batch.py
dosemetrics/utils/compliance.py
dosemetrics/utils/plot.py
dosemetrics-0.3.0.dist-info/licenses/LICENSE
dosemetrics_app/__init__.py
dosemetrics_app/app.py
dosemetrics_app/utils.py
dosemetrics_app/tabs/__init__.py
dosemetrics_app/tabs/calculate_dvh.py
dosemetrics_app/tabs/compliance_tab.py
dosemetrics_app/tabs/comprehensive_analysis.py
dosemetrics_app/tabs/conformity_tab.py
dosemetrics_app/tabs/gamma_tab.py
dosemetrics_app/tabs/geometric_tab.py
dosemetrics_app/tabs/homogeneity_tab.py
dosemetrics_app/tabs/instructions.py
dosemetrics_app/tabs/statistics_tab.py
dosemetrics_app/tabs/visualize_dose.py
dosemetrics_cli/__init__.py
dosemetrics_cli/__main__.py
dosemetrics-0.3.0.dist-info/METADATA
dosemetrics-0.3.0.dist-info/WHEEL
dosemetrics-0.3.0.dist-info/entry_points.txt
dosemetrics-0.3.0.dist-info/top_level.txt
dosemetrics-0.3.0.dist-info/RECORD
