Metadata-Version: 2.4
Name: dosemetrics
Version: 0.3.0
Summary: Measuring radiotherapy doses - plotting visualizations
Author-email: Amith Kamath <amith.kamath@unibe.ch>
License: Creative Commons Attribution-ShareAlike-NonCommercial 4.0 International License
Project-URL: Homepage, https://github.com/contouraid/dosemetrics
Project-URL: Repository, https://github.com/contouraid/dosemetrics
Project-URL: Issues, https://github.com/contouraid/dosemetrics/issues
Keywords: medical image analysis,machine learning,neuro,radiotherapy,dose metrics
Classifier: Development Status :: 3 - Alpha
Classifier: Intended Audience :: Developers
Classifier: Intended Audience :: Science/Research
Classifier: License :: Other/Proprietary License
Classifier: Natural Language :: English
Classifier: Programming Language :: Python :: 3.9
Classifier: Programming Language :: Python :: 3.10
Classifier: Programming Language :: Python :: 3.11
Classifier: Programming Language :: Python :: 3.12
Classifier: Topic :: Scientific/Engineering :: Image Recognition
Classifier: Topic :: Scientific/Engineering :: Mathematics
Classifier: Topic :: Scientific/Engineering :: Medical Science Apps.
Classifier: Topic :: Software Development :: Libraries :: Python Modules
Classifier: Topic :: Software Development :: Libraries
Requires-Python: >=3.9
License-File: LICENSE
Requires-Dist: altair~=5.4.0
Requires-Dist: gpssi>=0.1.2
Requires-Dist: huggingface_hub>=0.20.0
Requires-Dist: ipykernel>=6.0.0
Requires-Dist: matplotlib~=3.8.2
Requires-Dist: nbconvert>=7.16.6
Requires-Dist: nbformat>=5.10.4
Requires-Dist: nibabel==5.2.1
Requires-Dist: numba>=0.58.0
Requires-Dist: numpy~=1.26.2
Requires-Dist: pandas>=2.1.4
Requires-Dist: pillow==10.4.0
Requires-Dist: plotly~=5.23.0
Requires-Dist: pydicom>=2.3.0
Requires-Dist: pymedphys>=0.39.0
Requires-Dist: pymia>=0.3.4
Requires-Dist: pytest>=8.4.2
Requires-Dist: scikit-image>=0.21.0
Requires-Dist: scipy>=1.11.0
Requires-Dist: seaborn>=0.13.2
Requires-Dist: simpleitk>=2.4
Requires-Dist: streamlit~=1.45.0
Provides-Extra: docs
Requires-Dist: mkdocs>=1.5.0; extra == "docs"
Requires-Dist: mkdocs-material>=9.5.0; extra == "docs"
Requires-Dist: mkdocstrings[python]>=0.24.0; extra == "docs"
Requires-Dist: mkdocs-jupyter>=0.24.0; extra == "docs"
Requires-Dist: pymdown-extensions>=10.7; extra == "docs"
Provides-Extra: test
Requires-Dist: pytest-cov>=4.0.0; extra == "test"
Requires-Dist: nbformat>=5.0.0; extra == "test"
Requires-Dist: nbconvert>=7.0.0; extra == "test"
Requires-Dist: ipykernel>=6.0.0; extra == "test"
Dynamic: license-file
